pydantic_annotated/__init__.py
pydantic_annotated-0.0.1a0.dist-info/WHEEL
pydantic_annotated-0.0.1a0.dist-info/METADATA
pydantic_annotated-0.0.1a0.dist-info/RECORD
