Metadata-Version: 2.1
Name: pydantic-annotated
Version: 0.0.1a0
Summary: Generate Pydantic Fields with typing.Annotated
Home-page: http://github.com/JacobHayes/pydantic-annotated
License: MIT
Keywords: Annotated,pydantic,typing
Author: Jacob Hayes
Author-email: jacob.r.hayes@gmail.com
Requires-Python: >=3.9,<4.0
Classifier: Development Status :: 3 - Alpha
Classifier: License :: OSI Approved :: MIT License
Classifier: Programming Language :: Python :: 3
Classifier: Programming Language :: Python :: 3.9
Requires-Dist: pydantic
Project-URL: Repository, http://github.com/JacobHayes/pydantic-annotated
